core_model/__init__.py
core_model/app.py
core_model/dataset_manager.py
core_model/main.py
core_model-0.1.1.dist-info/METADATA
core_model-0.1.1.dist-info/WHEEL
core_model-0.1.1.dist-info/entry_points.txt
core_model-0.1.1.dist-info/top_level.txt
core_model-0.1.1.dist-info/RECORD
